[
    {
        "page_content": "Jadwal Praktikum Algoritma dan Struktur Data untuk Semester Genap 2024/2025 dapat diunduh. Dokumen ini berisi informasi waktu dan pembagian kelompok praktikum.",
        "metadata": {
            "source": "Layanan Kemahasiswaan.pdf",
            "category": "Layanan",
            "title": "Jadwal Praktikum Algoritma",
            "direct_link": "https://informatika.umsida.ac.id/wp-content/uploads/2025/03/PRAKTIKUM-ALGORITMA-DAN-STRUKTUR-DATA-2024-2025.pdf",
            "type": "pdf"
        }
    },
    {
        "page_content": "Jadwal Praktikum Basis Data untuk Semester Genap 2024/2025 tersedia untuk diunduh. Mahasiswa diharapkan memeriksa jadwal ini untuk kelancaran kegiatan praktikum.",
        "metadata": {
            "source": "Layanan Kemahasiswaan.pdf",
            "category": "Layanan",
            "title": "Jadwal Praktikum Basis Data",
            "direct_link": "https://informatika.umsida.ac.id/wp-content/uploads/2025/03/PRAKTIKUM-BASIS-DATA-2024-2025.pdf",
            "type": "pdf"
        }
    },
    {
        "page_content": "Jadwal Praktikum Pemrograman Berorientasi Objek (PBO) untuk Semester Genap 2024/2025 dapat diunduh melalui tautan yang disediakan.",
        "metadata": {
            "source": "Layanan Kemahasiswaan.pdf",
            "category": "Layanan",
            "title": "Jadwal Praktikum PBO",
            "direct_link": "https://informatika.umsida.ac.id/wp-content/uploads/2025/03/PRAKTIKUM-PBO-2024-2025.pdf",
            "type": "pdf"
        }
    },
    {
        "page_content": "Jadwal Praktikum Jaringan Komputer (Jarkom) untuk Semester Genap 2024/2025. Silakan unduh dokumen jadwal berikut.",
        "metadata": {
            "source": "Layanan Kemahasiswaan.pdf",
            "category": "Layanan",
            "title": "Jadwal Praktikum Jarkom",
            "direct_link": "https://informatika.umsida.ac.id/wp-content/uploads/2025/03/PRAKTIKUM-JARINGAN-KOMPUTER-2024-2025.pdf",
            "type": "pdf"
        }
    },
    {
        "page_content": "Layanan Administrasi Mahasiswa Informatika melayani tata persuratan secara online. Mahasiswa dapat mengajukan Suket Aktif Kuliah, Surat Keterangan Magang, Surat Penelitian, dan Surat Tugas Akhir melalui Google Form.",
        "metadata": {
            "source": "Layanan Kemahasiswaan.pdf",
            "category": "Layanan",
            "title": "Formulir Surat Online",
            "direct_link": "https://docs.google.com/forms/d/1ijKTVs1T546WUzqqEc9JeSfj2HoGVWFqhcGaIr-bs/viewform?edit_requested=true",
            "type": "google_form"
        }
    },
    {
        "page_content": "Laboratorium Informatika UMSIDA diperuntukkan bagi mahasiswa dan dosen untuk praktikum, riset, dan penelitian. Fasilitas ini mendukung pengembangan akademik.",
        "metadata": {
            "source": "Layanan Kemahasiswaan.pdf",
            "category": "Fasilitas",
            "title": "Laboratorium Umum"
        }
    },
    {
        "page_content": "Laboratorium Sistem Cerdas berfokus pada bidang Software Engineering, Programming, dan Computer Science. Lab ini mengembangkan basis kode untuk video game dan alat pengembangan perangkat lunak.",
        "metadata": {
            "source": "Layanan Kemahasiswaan.pdf",
            "category": "Fasilitas",
            "title": "Lab Sistem Cerdas"
        }
    },
    {
        "page_content": "Laboratorium Game dan Multimedia mengkoordinasikan tugas penciptaan video game, termasuk merancang karakter, level design, teka-teki, seni (art), dan animasi.",
        "metadata": {
            "source": "Layanan Kemahasiswaan.pdf",
            "category": "Fasilitas",
            "title": "Lab Game dan Multimedia"
        }
    },
    {
        "page_content": "Laboratorium Sistem Komputer dan Komunikasi Data berfokus pada analisis permasalahan jaringan, perekayasaan sistem, pengelolaan, serta evaluasi sistem jaringan.",
        "metadata": {
            "source": "Layanan Kemahasiswaan.pdf",
            "category": "Fasilitas",
            "title": "Lab Jaringan & Siskom"
        }
    },
    {
        "page_content": "Laboratorium Algoritma dan Pemrograman berfungsi sebagai penunjang kegiatan praktikum dasar, penelitian skripsi mahasiswa, serta riset dosen.",
        "metadata": {
            "source": "Layanan Kemahasiswaan.pdf",
            "category": "Fasilitas",
            "title": "Lab Algoritma"
        }
    },
    {
        "page_content": "Laboratorium Rekayasa Perangkat Lunak (RPL) melakukan analisis kebutuhan, perancangan, penjaminan kualitas (QA), dan rekayasa ulang perangkat lunak.",
        "metadata": {
            "source": "Layanan Kemahasiswaan.pdf",
            "category": "Fasilitas",
            "title": "Lab RPL"
        }
    },
    {
        "page_content": "Laboratorium Komputasi digunakan untuk menunjang praktikum lanjut, penelitian skripsi, dan riset dosen di lingkungan UMSIDA.",
        "metadata": {
            "source": "Layanan Kemahasiswaan.pdf",
            "category": "Fasilitas",
            "title": "Lab Komputasi"
        }
    },
    {
        "page_content": "Fasilitas Kampus: Kantin Universitas Muhammadiyah Sidoarjo.",
        "metadata": {
            "source": "Layanan Kemahasiswaan.pdf",
            "category": "Fasilitas",
            "title": "Kantin",
            "image_url": "https://informatika.umsida.ac.id/wp-content/uploads/2024/02/IMG20231109131643-1-1024x768-1.jpg"
        }
    },
    {
        "page_content": "Fasilitas Kampus: Laboratorium Komputer Modern.",
        "metadata": {
            "source": "Layanan Kemahasiswaan.pdf",
            "category": "Fasilitas",
            "title": "Laboratorium",
            "image_url": "https://informatika.umsida.ac.id/wp-content/uploads/2024/02/WhatsApp-Image-2023-08-31-at-10.47.11-scaled.jpg"
        }
    },
    {
        "page_content": "Fasilitas Kampus: Masjid Kampus UMSIDA.",
        "metadata": {
            "source": "Layanan Kemahasiswaan.pdf",
            "category": "Fasilitas",
            "title": "Masjid",
            "image_url": "https://informatika.umsida.ac.id/wp-content/uploads/2024/02/masjidfix.jpg"
        }
    },
    {
        "page_content": "Fasilitas Kampus: Gedung Perkuliahan yang nyaman.",
        "metadata": {
            "source": "Layanan Kemahasiswaan.pdf",
            "category": "Fasilitas",
            "title": "Gedung Kuliah",
            "image_url": "https://informatika.umsida.ac.id/wp-content/uploads/2024/02/kamp2-drone-2-e1518201208452.jpg"
        }
    },
    {
        "page_content": "Fasilitas Kampus: Area Tempat Parkir yang luas.",
        "metadata": {
            "source": "Layanan Kemahasiswaan.pdf",
            "category": "Fasilitas",
            "title": "Parkir",
            "image_url": "https://informatika.umsida.ac.id/wp-content/uploads/2024/02/WhatsApp-Image-2023-08-31-at-10.47.08-scaled.jpg"
        }
    },
    {
        "page_content": "Fasilitas Kampus: Ruang Baca dan Perpustakaan.",
        "metadata": {
            "source": "Layanan Kemahasiswaan.pdf",
            "category": "Fasilitas",
            "title": "Ruang Baca",
            "image_url": "https://informatika.umsida.ac.id/wp-content/uploads/2024/02/WhatsApp-Image-2021-11-19-at-13.06.50-2-1024x768-1.jpeg"
        }
    },
    {
        "page_content": "Organisasi Mahasiswa: Asisten Laboratorium Informatika (ASLAB). Bertugas mewujudkan laboratorium bermutu nasional, menyelenggarakan praktikum berkualitas, dan menyediakan sarana penelitian.",
        "metadata": {
            "source": "Layanan Kemahasiswaan.pdf",
            "category": "Organisasi",
            "title": "ASLAB",
            "web_link": "https://informatika.umsida.ac.id/seocrawler/search-engine-optimization/",
            "instagram_link": "https://www.instagram.com/aslabinf.umsida/"
        }
    },
    {
        "page_content": "Organisasi Mahasiswa: Himpunan Mahasiswa Informatika (HIMATIKA). Wadah pengembangan pola pikir, kepribadian, dan potensi intelektual mahasiswa yang kompetitif serta berlandaskan nilai Islam.",
        "metadata": {
            "source": "Layanan Kemahasiswaan.pdf",
            "category": "Organisasi",
            "title": "HIMATIKA",
            "web_link": "https://informatika.umsida.ac.id/seocrawler/code-optimization/",
            "instagram_link": "https://www.instagram.com/himatika_umsida/"
        }
    },
    {
        "page_content": "Praktikum adalah kegiatan akademik wajib bagi mahasiswa Prodi Informatika. Terdapat 9 jenis praktikum yang harus diikuti, yaitu: Praktikum Algoritma dan Pemrograman, Sistem Digital, Algoritma dan Struktur Data, Basis Data, Jaringan Komputer, Sistem Operasi, Pemrograman Berbasis Web, Pemrograman Berorientasi Objek (PBO), dan Rekayasa Perangkat Lunak[cite: 70].",
        "metadata": {
            "source": "Program Akademik.pdf",
            "category": "Program Akademik",
            "title": "Daftar Praktikum Wajib"
        }
    },
    {
        "page_content": "Lembaga Sertifikasi Profesi (LSP) Informatika UMSIDA bertanggung jawab melaksanakan sertifikasi kompetensi profesi yang teregistrasi BNSP. Skema yang tersedia adalah 'Junior Network Administrator'. [cite_start]Tugas LSP meliputi mengembangkan standar kompetensi, melaksanakan uji kompetensi, menerbitkan sertifikat, dan melakukan akreditasi Tempat Uji Kompetensi[cite: 71, 72, 73].",
        "metadata": {
            "source": "Program Akademik.pdf",
            "category": "Sertifikasi",
            "title": "LSP dan Sertifikasi Kompetensi"
        }
    },
    {
        "page_content": "Pelatihan atau Workshop rutin diadakan untuk meningkatkan keterampilan softskill dan hardskill mahasiswa di bidang teknologi. [cite_start]Contoh kegiatan yang pernah diadakan antara lain: Workshop 'Mulai dari 0, Belajar Web Development', Seminar 'Learning Python For Beginner', dan Workshop 'Machine Learning with Python'[cite: 75, 76, 77].",
        "metadata": {
            "source": "Program Akademik.pdf",
            "category": "Kegiatan Penunjang",
            "title": "Pelatihan dan Workshop"
        }
    },
    {
        "page_content": "Program Magang Bersertifikat berlangsung selama 1-2 semester. Program ini memberikan pengalaman industri agar mahasiswa siap memasuki dunia kerja. [cite_start]Keuntungan lainnya adalah industri mendapatkan talenta yang cocok untuk direkrut langsung, serta mahasiswa dapat mengaplikasikan keilmuannya secara maksimal[cite: 79, 80].",
        "metadata": {
            "source": "Program Akademik.pdf",
            "category": "Program MBKM",
            "title": "Magang Bersertifikat"
        }
    },
    {
        "page_content": "Program Pertukaran Mahasiswa merupakan program mobilitas selama satu semester untuk belajar di perguruan tinggi lain di Indonesia. Program ini bertujuan meningkatkan softskills dan hardskills serta memperkuat persatuan. [cite_start]Nilai dan SKS yang diambil di perguruan tinggi luar akan disetarakan oleh perguruan tinggi asal[cite: 81, 82, 83, 84].",
        "metadata": {
            "source": "Program Akademik.pdf",
            "category": "Program MBKM",
            "title": "Pertukaran Mahasiswa"
        }
    },
    {
        "page_content": "Studi Proyek Independen Bersertifikat memungkinkan mahasiswa mengembangkan proyek berdasarkan topik sosial khusus secara berkelompok. [cite_start]Tujuannya adalah memecahkan permasalahan di masyarakat, melatih kepekaan sosial, dan mendalami penyelesaian masalah sesuai minat dan keahlian masing-masing[cite: 85, 86, 87].",
        "metadata": {
            "source": "Program Akademik.pdf",
            "category": "Program MBKM",
            "title": "Studi Proyek Independen"
        }
    },
    {
        "page_content": "Praktikum adalah kegiatan akademik wajib bagi mahasiswa Prodi Informatika. Terdapat 9 jenis praktikum yang harus diikuti, yaitu: Praktikum Algoritma dan Pemrograman, Sistem Digital, Algoritma dan Struktur Data, Basis Data, Jaringan Komputer, Sistem Operasi, Pemrograman Berbasis Web, Pemrograman Berorientasi Objek (PBO), dan Rekayasa Perangkat Lunak[cite: 70].",
        "metadata": {
            "source": "Program Akademik.pdf",
            "category": "Program Akademik",
            "title": "Daftar Praktikum Wajib"
        }
    },
    {
        "page_content": "Lembaga Sertifikasi Profesi (LSP) Informatika UMSIDA bertanggung jawab melaksanakan sertifikasi kompetensi profesi yang teregistrasi BNSP. Skema yang tersedia adalah 'Junior Network Administrator'. [cite_start]Tugas LSP meliputi mengembangkan standar kompetensi, melaksanakan uji kompetensi, menerbitkan sertifikat, dan melakukan akreditasi Tempat Uji Kompetensi[cite: 71, 72, 73].",
        "metadata": {
            "source": "Program Akademik.pdf",
            "category": "Sertifikasi",
            "title": "LSP dan Sertifikasi Kompetensi"
        }
    },
    {
        "page_content": "Pelatihan atau Workshop rutin diadakan untuk meningkatkan keterampilan softskill dan hardskill mahasiswa di bidang teknologi. [cite_start]Contoh kegiatan yang pernah diadakan antara lain: Workshop 'Mulai dari 0, Belajar Web Development', Seminar 'Learning Python For Beginner', dan Workshop 'Machine Learning with Python'[cite: 75, 76, 77].",
        "metadata": {
            "source": "Program Akademik.pdf",
            "category": "Kegiatan Penunjang",
            "title": "Pelatihan dan Workshop"
        }
    },
    {
        "page_content": "Program Magang Bersertifikat berlangsung selama 1-2 semester. Program ini memberikan pengalaman industri agar mahasiswa siap memasuki dunia kerja. [cite_start]Keuntungan lainnya adalah industri mendapatkan talenta yang cocok untuk direkrut langsung, serta mahasiswa dapat mengaplikasikan keilmuannya secara maksimal[cite: 79, 80].",
        "metadata": {
            "source": "Program Akademik.pdf",
            "category": "Program MBKM",
            "title": "Magang Bersertifikat"
        }
    },
    {
        "page_content": "Program Pertukaran Mahasiswa merupakan program mobilitas selama satu semester untuk belajar di perguruan tinggi lain di Indonesia. Program ini bertujuan meningkatkan softskills dan hardskills serta memperkuat persatuan. [cite_start]Nilai dan SKS yang diambil di perguruan tinggi luar akan disetarakan oleh perguruan tinggi asal[cite: 81, 82, 83, 84].",
        "metadata": {
            "source": "Program Akademik.pdf",
            "category": "Program MBKM",
            "title": "Pertukaran Mahasiswa"
        }
    },
    {
        "page_content": "Studi Proyek Independen Bersertifikat memungkinkan mahasiswa mengembangkan proyek berdasarkan topik sosial khusus secara berkelompok. [cite_start]Tujuannya adalah memecahkan permasalahan di masyarakat, melatih kepekaan sosial, dan mendalami penyelesaian masalah sesuai minat dan keahlian masing-masing[cite: 85, 86, 87].",
        "metadata": {
            "source": "Program Akademik.pdf",
            "category": "Program MBKM",
            "title": "Studi Proyek Independen"
        }
    },
    {
        "page_content": "Daftar mata kuliah Semester 1 Program Studi Informatika UMSIDA meliputi: Kemanusiaan dan Keimanan (2 sks), Algoritma dan Pemrograman (4 sks), Sistem Digital (4 sks), Arsitektur dan Organisasi Komputer (3 sks), Kalkulus (3 sks), dan Fisika (3 sks). Total beban studi semester ini adalah dasar penguatan logika dan sains.",
        "metadata": {
            "source": "Sebaran Mata Kuliah.pdf",
            "category": "Kurikulum",
            "semester": "1",
            "title": "Mata Kuliah Semester 1"
        }
    },
    {
        "page_content": "Daftar mata kuliah Semester 2 Program Studi Informatika UMSIDA meliputi: Ibadah Akhlak dan Muamalah (2 sks), Algoritma dan Struktur Data (4 sks), Basis Data (4 sks), Interaksi Manusia dan Komputer (3 sks), Matematika Diskrit (3 sks), dan Teori Bahasa dan Otomata (3 sks). Fokus semester ini adalah penguatan dasar pemrograman dan data.",
        "metadata": {
            "source": "Sebaran Mata Kuliah.pdf",
            "category": "Kurikulum",
            "semester": "2",
            "title": "Mata Kuliah Semester 2"
        }
    },
    {
        "page_content": "Daftar mata kuliah Semester 3 Program Studi Informatika UMSIDA meliputi: Kemuhammadiyahan (2 sks), Pemrograman Berbasis Web (4 sks), Matematika Rekayasa (3 sks), Aljabar Linier (3 sks), Sistem Informasi (3 sks), dan Sistem Operasi (4 sks). Mahasiswa mulai mempelajari pengembangan web dan sistem operasi.",
        "metadata": {
            "source": "Sebaran Mata Kuliah.pdf",
            "category": "Kurikulum",
            "semester": "3",
            "title": "Mata Kuliah Semester 3"
        }
    },
    {
        "page_content": "Daftar mata kuliah Semester 4 Program Studi Informatika UMSIDA meliputi: Sains dan Teknologi Islam (2 sks), Metode Numerik (3 sks), Statistika dan Probabilitas (3 sks), Jaringan Komputer (4 sks), Pemrograman Berorientasi Objek (4 sks), Audit Sistem (3 sks), dan Pengembangan Aplikasi Berbasis Web (3 sks).",
        "metadata": {
            "source": "Sebaran Mata Kuliah.pdf",
            "category": "Kurikulum",
            "semester": "4",
            "title": "Mata Kuliah Semester 4"
        }
    },
    {
        "page_content": "Daftar mata kuliah Semester 5 Program Studi Informatika UMSIDA meliputi: Rekayasa Perangkat Lunak (3 sks), Pemodelan Game (3 sks), Magang Industri (3 sks), Grafika Komputer (3 sks), Kecerdasan Buatan (3 sks), Pemrograman Mobile (3 sks), Data Mining (3 sks), dan Metodologi Penelitian (2 sks).",
        "metadata": {
            "source": "Sebaran Mata Kuliah.pdf",
            "category": "Kurikulum",
            "semester": "5",
            "title": "Mata Kuliah Semester 5"
        }
    },
    {
        "page_content": "Daftar mata kuliah Semester 6 Program Studi Informatika UMSIDA meliputi: Kewirausahaan (3 sks), Machine Learning (3 sks), Teknik Optimasi (3 sks), Pengolahan Citra Digital (3 sks), dan Kuliah Kerja Nyata (3 sks). Selain itu, mahasiswa mengambil Mata Kuliah Pilihan 1 (3 sks) dan Mata Kuliah Pilihan 2 (3 sks).",
        "metadata": {
            "source": "Sebaran Mata Kuliah.pdf",
            "category": "Kurikulum",
            "semester": "6",
            "title": "Mata Kuliah Semester 6"
        }
    },
    {
        "page_content": "Daftar mata kuliah Semester 7 Program Studi Informatika UMSIDA meliputi: Kewarganegaraan (2 sks), Bahasa Inggris (2 sks), Bahasa Indonesia (2 sks), Pancasila (2 sks), dan Etika Profesi (2 sks). Mahasiswa juga mengambil Mata Kuliah Pilihan 3 (3 sks) dan Mata Kuliah Pilihan 4 (3 sks).",
        "metadata": {
            "source": "Sebaran Mata Kuliah.pdf",
            "category": "Kurikulum",
            "semester": "7",
            "title": "Mata Kuliah Semester 7"
        }
    },
    {
        "page_content": "Daftar mata kuliah Semester 8 Program Studi Informatika UMSIDA hanya berfokus pada tugas akhir, yaitu Skripsi dengan bobot 6 SKS.",
        "metadata": {
            "source": "Sebaran Mata Kuliah.pdf",
            "category": "Kurikulum",
            "semester": "8",
            "title": "Mata Kuliah Semester 8"
        }
    },
    {
        "page_content": "Daftar Mata Kuliah Pilihan untuk Semester 6 meliputi: IoT Technology (3 sks), Pengamanan Sistem Komputer (3 sks), Pemrograman Terdistribusi (3 sks), dan Manajemen Proyek Teknologi Informasi (3 sks). Mahasiswa dapat memilih sesuai minat spesialisasi.",
        "metadata": {
            "source": "Sebaran Mata Kuliah.pdf",
            "category": "Kurikulum",
            "semester": "Pilihan Semester 6",
            "title": "Mata Kuliah Pilihan Sem 6"
        }
    },
    {
        "page_content": "Daftar Mata Kuliah Pilihan untuk Semester 7 meliputi: Desain dan Aplikasi Multimedia (3 sks), Pemrograman Game (3 sks), Web dan Text Mining (3 sks), dan Ethical Hacking (3 sks). Mahasiswa dapat memilih untuk memperdalam keahlian teknis tertentu.",
        "metadata": {
            "source": "Sebaran Mata Kuliah.pdf",
            "category": "Kurikulum",
            "semester": "Pilihan Semester 7",
            "title": "Mata Kuliah Pilihan Sem 7"
        }
    },
    {
        "page_content": "Visi Program Studi Informatika UMSIDA adalah menghasilkan lulusan yang profesional, unggul, inovatif, dan kompetitif dalam rekayasa perangkat lunak dan sistem cerdas yang adaptif terhadap perkembangan IPTEKS berdasarkan nilai-nilai Islam untuk kesejahteraan masyarakat tingkat ASEAN pada tahun 2038.",
        "metadata": {
            "source": "Visi dan Misi.pdf",
            "category": "Profil Prodi",
            "title": "Visi Program Studi"
        }
    },
    {
        "page_content": "Misi Program Studi Informatika UMSIDA meliputi: 1. Menyelenggarakan pendidikan dan pengajaran unggul serta inovatif dalam pengembangan IPTEKS berbasis nilai Islam. 2. Melakukan penelitian pengembangan IPTEKS untuk kesejahteraan masyarakat. 3. Melaksanakan pengabdian masyarakat bereputasi internasional. 4. Mengembangkan kerjasama berkelanjutan dengan instansi dalam dan luar negeri. 5. Meningkatkan tata kelola profesional. 6. Pembinaan kemahasiswaan yang unggul dan inovatif.",
        "metadata": {
            "source": "Visi dan Misi.pdf",
            "category": "Profil Prodi",
            "title": "Misi Program Studi"
        }
    },
    {
        "page_content": "Tujuan Program Studi Informatika UMSIDA adalah: 1. Menghasilkan lulusan unggul, inovatif, dan profesional berbasis nilai Islam. 2. Menghasilkan produk penelitian Informatika yang mendukung pembelajaran. 3. Menghasilkan teknologi tepat guna bereputasi internasional. 4. Menjalin kerjasama berkelanjutan di bidang pendidikan dan penelitian. 5. Meningkatkan tata kelola profesional serta pembinaan kemahasiswaan yang inovatif.",
        "metadata": {
            "source": "Visi dan Misi.pdf",
            "category": "Profil Prodi",
            "title": "Tujuan Program Studi"
        }
    },
    {
        "page_content": "Profil Lulusan Informatika UMSIDA diharapkan memiliki kompetensi: 1. Berkarakter uswah dalam inovasi teknologi dan mampu bersinergi dalam tim. 2. Mampu menganalisis persoalan computing dan menerapkan solusinya secara dinamis. 3. Mampu mendesain, mengimplementasi, dan mengevaluasi solusi berbasis computing secara mandiri. 4. Mampu berkomunikasi dengan baik, bersaing, dan bekerjasama dalam dunia kerja profesional.",
        "metadata": {
            "source": "Visi dan Misi.pdf",
            "category": "Profil Prodi",
            "title": "Profil Lulusan"
        }
    }
]